{
  "build": {
    "buildNumber": "14",
    "buildId": "20679611141",
    "buildUrl": "https://github.com/ThiruDev50/dev-tools-code/actions/runs/20679611141",
    "triggeredBy": "ThiruDev50",
    "workflow": "Devtools CI",
    "buildDate": "2026-01-03T16:04:54Z",
    "buildTimestamp": 1767456294
  },
  "source": {
    "branch": "master",
    "commit": {
      "sha": "eb8ce89466274c0f69fc1b4f7daabfd708f4f2c7",
      "shortSha": "eb8ce89",
      "message": "Routing with proper query params",
      "author": "ThiruDev50",
      "authorEmail": "thiru.dev50@mail.com",
      "date": "2026-01-03T21:32:06+05:30",
      "url": "https://github.com/ThiruDev50/dev-tools-code/commit/eb8ce89466274c0f69fc1b4f7daabfd708f4f2c7"
    },
    "repository": {
      "name": "ThiruDev50/dev-tools-code",
      "url": "https://github.com/ThiruDev50/dev-tools-code"
    }
  },
  "deployment": {
    "deploymentNumber": "9",
    "deploymentId": "20679638610",
    "deploymentUrl": "https://github.com/ThiruDev50/dev-tools-code/actions/runs/20679638610",
    "deployedBy": "ThiruDev50",
    "deploymentDate": "2026-01-03T16:06:18Z",
    "deploymentTimestamp": 1767456378,
    "ciBuildNumber": "14",
    "ciRunId": "20679611141",
    "ciArtifactName": "genetom-devtools-14",
    "targetRepository": "ThiruDev50/devtools",
    "targetBranch": "main"
  }
}
